lmhprint/__init__.py
lmhprint/lmhprint.py
lmhprint-0.1.dist-info/LICENSE
lmhprint-0.1.dist-info/METADATA
lmhprint-0.1.dist-info/WHEEL
lmhprint-0.1.dist-info/top_level.txt
lmhprint-0.1.dist-info/RECORD
