Metadata-Version: 2.1
Name: lmhprint
Version: 0.1
Summary: random color print
Home-page: https://github.com/lmhsky/_print
Author: lmhsky
Author-email: lmhtowork@gmail.com
License: MIT
Platform: UNKNOWN
License-File: LICENSE
